AlgoPlus/CTPV6315.cpython-37m-x86_64-linux-gnu.so
AlgoPlus/_AlgoPlusCTPV6315.so
AlgoPlus/__init__.py
AlgoPlus/libAlgoPlusCTPV6315Py37.so
AlgoPlus/libthostmduserapi_se.so
AlgoPlus/libthosttraderapi_se.so
AlgoPlusCTPV6315-0.3.dist-info/METADATA
AlgoPlusCTPV6315-0.3.dist-info/RECORD
AlgoPlusCTPV6315-0.3.dist-info/WHEEL
AlgoPlusCTPV6315-0.3.dist-info/top_level.txt
