Metadata-Version: 2.1
Name: AlgoPlusCTPV6315
Version: 0.3
Summary: CTP模拟交易API
Home-page: http://algo.plus
Author: www.algo.plus
Author-email: algo@algo.com
License: UNKNOWN
Keywords: 期货 Simnow CTP NSight 奇点
Platform: Windows
Platform: Linux
Requires-Python: >=3.7
